src/__init__.py
src/main.py
dj_obj-1.0.2.dist-info/LICENSE
dj_obj-1.0.2.dist-info/METADATA
dj_obj-1.0.2.dist-info/WHEEL
dj_obj-1.0.2.dist-info/top_level.txt
dj_obj-1.0.2.dist-info/RECORD
