Metadata-Version: 2.1
Name: dj-obj
Version: 1.0.2
Home-page: https://github.com/lum0vi/new_library
Author: SODT
Author-email: svsharygin@icloud.com
Project-URL: Documentation, https://github.com/lum0vi/new_library
Keywords: example python
Classifier: Programming Language :: Python :: 3.11
Classifier: License :: OSI Approved :: MIT License
Classifier: Operating System :: OS Independent
Requires-Python: >=3.9
License-File: LICENSE
Requires-Dist: requests >=2.25.1
